automatata/__init__.py
automatata/models/__init__.py
automatata/models/dfa.py
automatata-0.0.1.dist-info/LICENSE
automatata-0.0.1.dist-info/METADATA
automatata-0.0.1.dist-info/WHEEL
automatata-0.0.1.dist-info/top_level.txt
automatata-0.0.1.dist-info/RECORD
