Metadata-Version: 2.1
Name: automatata
Version: 0.0.1
Summary: Automata in Python.
Author-email: Bruno Lange <blangeram@gmail.com>
Classifier: Programming Language :: Python :: 3
Classifier: License :: OSI Approved :: MIT License
Classifier: Operating System :: OS Independent
Requires-Python: >=3.10
License-File: LICENSE
